distribution_practice/__init__.py
distribution_practice/calculator.py
distribution_practice-0.0.1.dist-info/LICENSE
distribution_practice-0.0.1.dist-info/METADATA
distribution_practice-0.0.1.dist-info/WHEEL
distribution_practice-0.0.1.dist-info/top_level.txt
distribution_practice-0.0.1.dist-info/RECORD
