Metadata-Version: 2.2
Name: distribution_practice
Version: 0.0.1
Summary: A simple library with one function 'add(a, b)'. 
Home-page: https://github.com/tdhdjv/DistrubutionPractice
Author: tdhdjv
License: Apache Software License
Classifier: License :: OSI Approved :: Apache Software License
Classifier: Programming Language :: Python :: 3.13
Requires-Python: >=3.0
License-File: LICENSE
Provides-Extra: dev
Requires-Dist: pytest>=8.0; extra == "dev"
Requires-Dist: twine; extra == "dev"
Dynamic: author
Dynamic: classifier
Dynamic: description
Dynamic: description-content-type
Dynamic: home-page
Dynamic: license
Dynamic: provides-extra
Dynamic: requires-python
Dynamic: summary
